olo_client-0.5.1.dist-info/licenses/LICENSE
oloclient/__init__.py
oloclient/_version.py
oloclient/_version_loader.py
oloclient/auth.py
oloclient/client.py
oloclient/core.py
oloclient/globals.py
oloclient/joint.py
oloclient/logs.py
oloclient/navigation.py
oloclient/rosbag_recording.py
oloclient/video.py
oloclient/video_recording.py
oloclient/vision.py
olo_client-0.5.1.dist-info/METADATA
olo_client-0.5.1.dist-info/WHEEL
olo_client-0.5.1.dist-info/top_level.txt
olo_client-0.5.1.dist-info/RECORD
